{"context": {"characters": {"list_display_order": "qa,hf,tr", "qa": {"name": "Captain Elias", "essence": "Weathered lighthouse keeper", "appearance": "Grizzled, with a salt-and-pepper beard", "character_age": "60 years old", "clothing": "Worn fisherman's sweater and cap"}, "hf": {"name": "Marina", "essence": "Lost soul seeking redemption", "appearance": "Ethereal, with flowing white hair", "character_age": "Ageless", "clothing": "Tattered white dress"}, "tr": {"name": "Finn", "essence": "Young sailor trapped between worlds", "appearance": "Youthful, with haunted eyes", "character_age": "25 years old", "clothing": "Vintage sailor uniform"}}}, "json_to_edit": {"voice_over": "In the realm between worlds, a beacon of hope shines through the mist.", "description": "A mysterious lighthouse guides lost souls through a spectral fog.", "location": "Coastal cliffs", "lighting": "Ethereal, misty glow", "weather": "Foggy", "ambience_sound_keywords": "Crashing waves, distant foghorn, whispers in the wind", "number_of_shots": "10", "name": "Lighthouse of Lost Souls", "scene_summary": "Captain Elias tends to the lighthouse, guiding Marina and Finn towards redemption.", "shots": {"list_display_order": "qa,hf,tr,xc,ka,fn,af,qo,fp,va", "qa": {"type": "Establishing shot", "sfx_keywords": "crashing waves, foghorn", "action": "A majestic lighthouse stands tall on rugged cliffs, piercing through dense fog."}, "hf": {"type": "Wide shot", "sfx_keywords": "wind howling, creaking wood", "action": "Captain Elias climbs the winding staircase, his lantern casting dancing shadows."}, "tr": {"type": "Medium shot", "sfx_keywords": "mechanical clicks, glass polishing", "action": "The Captain meticulously cleans the massive lighthouse lens, his weathered hands working with practiced precision."}, "xc": {"type": "Close-up", "sfx_keywords": "whispers in the wind, soft footsteps", "action": "Marina's ethereal form materializes at the base of the lighthouse, her eyes fixed on the beacon above."}, "ka": {"type": "Wide shot", "sfx_keywords": "distant ship bell, muffled voices", "action": "Finn's ghostly ship emerges from the fog, drawn to the lighthouse's powerful beam."}, "fn": {"type": "Medium shot", "sfx_keywords": "creaking floorboards, soft gasps", "action": "Captain Elias encounters Marina on the lighthouse balcony, his eyes widening in recognition."}, "af": {"type": "Close-up", "sfx_keywords": "heartbeat, whispering voices", "action": "Finn's face appears in the ship's porthole, a mix of hope and fear in his eyes."}, "qo": {"type": "Wide shot", "sfx_keywords": "crashing waves, wind chimes", "action": "The lighthouse beam sweeps across the turbulent sea, illuminating Finn's approaching vessel."}, "fp": {"type": "Medium shot", "sfx_keywords": "creaking rope, splashing water", "action": "Finn climbs a spectral ladder from his ship to the lighthouse rocks, reaching for Marina's outstretched hand."}, "va": {"type": "Close-up", "sfx_keywords": "soft humming, ethereal chimes", "action": "The lighthouse lens flares brightly as Captain Elias, Marina, and Finn stand together, bathed in its redemptive light."}}}, "edit_command": "Add a new shot after every three existing shots, but don't change anything else in the scene.", "label": {"updated_json": {"voice_over": "In the realm between worlds, a beacon of hope shines through the mist.", "description": "A mysterious lighthouse guides lost souls through a spectral fog.", "location": "Coastal cliffs", "lighting": "Ethereal, misty glow", "weather": "Foggy", "ambience_sound_keywords": "Crashing waves, distant foghorn, whispers in the wind", "number_of_shots": "13", "name": "Lighthouse of Lost Souls", "scene_summary": "Captain Elias tends to the lighthouse, guiding Marina and Finn towards redemption.", "shots": {"list_display_order": "qa,hf,tr,bx,xc,ka,fn,yz,af,qo,fp,lm,va", "qa": {"type": "Establishing shot", "sfx_keywords": "crashing waves, foghorn", "action": "A majestic lighthouse stands tall on rugged cliffs, piercing through dense fog."}, "hf": {"type": "Wide shot", "sfx_keywords": "wind howling, creaking wood", "action": "Captain Elias climbs the winding staircase, his lantern casting dancing shadows."}, "tr": {"type": "Medium shot", "sfx_keywords": "mechanical clicks, glass polishing", "action": "The Captain meticulously cleans the massive lighthouse lens, his weathered hands working with practiced precision."}, "bx": {"type": "Aerial shot", "sfx_keywords": "whistling wind, distant seagulls", "action": "The camera soars around the lighthouse, revealing its isolated position on the misty coastline."}, "xc": {"type": "Close-up", "sfx_keywords": "whispers in the wind, soft footsteps", "action": "Marina's ethereal form materializes at the base of the lighthouse, her eyes fixed on the beacon above."}, "ka": {"type": "Wide shot", "sfx_keywords": "distant ship bell, muffled voices", "action": "Finn's ghostly ship emerges from the fog, drawn to the lighthouse's powerful beam."}, "fn": {"type": "Medium shot", "sfx_keywords": "creaking floorboards, soft gasps", "action": "Captain Elias encounters Marina on the lighthouse balcony, his eyes widening in recognition."}, "yz": {"type": "Tracking shot", "sfx_keywords": "echoing footsteps, whispered memories", "action": "The camera follows Marina as she glides through the lighthouse, her presence stirring long-forgotten echoes."}, "af": {"type": "Close-up", "sfx_keywords": "heartbeat, whispering voices", "action": "Finn's face appears in the ship's porthole, a mix of hope and fear in his eyes."}, "qo": {"type": "Wide shot", "sfx_keywords": "crashing waves, wind chimes", "action": "The lighthouse beam sweeps across the turbulent sea, illuminating Finn's approaching vessel."}, "fp": {"type": "Medium shot", "sfx_keywords": "creaking rope, splashing water", "action": "Finn climbs a spectral ladder from his ship to the lighthouse rocks, reaching for Marina's outstretched hand."}, "lm": {"type": "Low angle shot", "sfx_keywords": "rumbling thunder, ethereal humming", "action": "The lighthouse towers above, its light pulsing with increasing intensity as the three souls draw closer together."}, "va": {"type": "Close-up", "sfx_keywords": "soft humming, ethereal chimes", "action": "The lighthouse lens flares brightly as Captain Elias, Marina, and Finn stand together, bathed in its redemptive light."}}}, "is_unsupported": false, "rationale": "we will add new shots after every three existing shots in the scene, as requested by the edit command. this will increase the total number of shots from 10 to 13. we'll insert creative and fitting shots that complement the existing scene without altering any other elements. the new shots will be added after the third, sixth, and ninth shots in the current order. we'll update the list_display_order and add the new shots to the dictionary, using random two-letter keys for each new shot."}, "json_diff": [{"op": "replace", "path": "/number_of_shots", "value": "13"}, {"op": "add", "path": "/shots/bx", "value": {"type": "Aerial shot", "sfx_keywords": "whistling wind, distant seagulls", "action": "The camera soars around the lighthouse, revealing its isolated position on the misty coastline."}}, {"op": "add", "path": "/shots/yz", "value": {"type": "Tracking shot", "sfx_keywords": "echoing footsteps, whispered memories", "action": "The camera follows Marina as she glides through the lighthouse, her presence stirring long-forgotten echoes."}}, {"op": "add", "path": "/shots/lm", "value": {"type": "Low angle shot", "sfx_keywords": "rumbling thunder, ethereal humming", "action": "The lighthouse towers above, its light pulsing with increasing intensity as the three souls draw closer together."}}, {"op": "replace", "path": "/shots/list_display_order", "value": "qa,hf,tr,bx,xc,ka,fn,yz,af,qo,fp,lm,va"}], "validation_labels": []}