{"context": {"characters": {"list_display_order": "qa,hf,tr,xc", "qa": {"name": "Emily", "essence": "Curious and determined historian", "appearance": "Petite with glasses and curly hair", "character_age": "32 years old", "clothing": "Casual sweater and jeans"}, "hf": {"name": "Marcus", "essence": "Skeptical but supportive friend", "appearance": "Tall with a beard and kind eyes", "character_age": "35 years old", "clothing": "Comfortable flannel shirt and khakis"}, "tr": {"name": "Grandma Rose", "essence": "Wise and mysterious elderly woman", "appearance": "Frail with silver hair and twinkling eyes", "character_age": "85 years old", "clothing": "Floral dress and cardigan"}, "xc": {"name": "The Book", "essence": "Magical artifact with a mind of its own", "appearance": "Ancient leather-bound tome with glowing symbols", "character_age": "Centuries old", "clothing": "N/A"}}}, "json_to_edit": {"voice_over": "Sometimes, the past whispers its secrets through the most unexpected channels.", "description": "Emily discovers a mysterious talking book that reveals forgotten family history.", "location": "Emily's cozy attic study", "lighting": "Warm, golden afternoon light", "weather": "Sunny with occasional clouds", "ambience_sound_keywords": "Creaking floorboards, rustling pages, distant wind chimes", "number_of_shots": "6", "name": "Whispers from the Past", "scene_summary": "Emily, along with Marcus and Grandma Rose, uncovers family secrets through a magical talking book.", "shots": {"list_display_order": "qa,hf,tr,xc,ka,fn", "qa": {"type": "Wide-shot", "sfx_keywords": "creaking floorboards, dust particles", "action": "Emily and Marcus enter the cluttered attic study, sunlight streaming through a small window."}, "hf": {"type": "Close-up", "sfx_keywords": "book pages rustling", "action": "Emily's hands brush over the ancient tome, causing it to glow faintly."}, "tr": {"type": "Medium-shot", "sfx_keywords": "magical humming, gasps", "action": "The book levitates and opens, startling Emily and Marcus."}, "xc": {"type": "Over-the-shoulder", "sfx_keywords": "whispered voices, wind chimes", "action": "Emily, Marcus, and Grandma Rose huddle around the floating book as it speaks in riddles."}, "ka": {"type": "Close-up", "sfx_keywords": "heartbeat, soft sobs", "action": "Tears form in Grandma Rose's eyes as she recognizes a long-forgotten family secret."}, "fn": {"type": "Wide-shot", "sfx_keywords": "magical whoosh, creaking furniture", "action": "The attic transforms momentarily, showing glimpses of the past as the book's magic intensifies."}}}, "edit_command": "Remove the third shot of the levitating book.", "label": {"updated_json": {"voice_over": "Sometimes, the past whispers its secrets through the most unexpected channels.", "description": "Emily discovers a mysterious talking book that reveals forgotten family history.", "location": "Emily's cozy attic study", "lighting": "Warm, golden afternoon light", "weather": "Sunny with occasional clouds", "ambience_sound_keywords": "Creaking floorboards, rustling pages, distant wind chimes", "number_of_shots": "5", "name": "Whispers from the Past", "scene_summary": "Emily, along with Marcus and Grandma Rose, uncovers family secrets through a magical talking book.", "shots": {"list_display_order": "qa,hf,xc,ka,fn", "qa": {"type": "Wide-shot", "sfx_keywords": "creaking floorboards, dust particles", "action": "Emily and Marcus enter the cluttered attic study, sunlight streaming through a small window."}, "hf": {"type": "Close-up", "sfx_keywords": "book pages rustling", "action": "Emily's hands brush over the ancient tome, causing it to glow faintly."}, "xc": {"type": "Over-the-shoulder", "sfx_keywords": "whispered voices, wind chimes", "action": "Emily, Marcus, and Grandma Rose huddle around the floating book as it speaks in riddles."}, "ka": {"type": "Close-up", "sfx_keywords": "heartbeat, soft sobs", "action": "Tears form in Grandma Rose's eyes as she recognizes a long-forgotten family secret."}, "fn": {"type": "Wide-shot", "sfx_keywords": "magical whoosh, creaking furniture", "action": "The attic transforms momentarily, showing glimpses of the past as the book's magic intensifies."}}}, "is_unsupported": false, "rationale": "we need to remove the third shot of the levitating book from the scene. this corresponds to the shot with the key \"tr\" in the json. to do this, we'll need to update the \"list_display_order\" in the \"shots\" object and remove the \"tr\" entry from the shots dictionary. this will effectively remove the shot where \"the book levitates and opens, startling emily and marcus.\" we'll keep all other shots and scene details intact, maintaining the overall flow of the scene while removing this specific magical moment. this change slightly alters the pacing and reveal of the book's magical nature, but it doesn't fundamentally change the scene's core concept of discovering family secrets through a magical book."}, "json_diff": [{"op": "replace", "path": "/number_of_shots", "value": "5"}, {"op": "remove", "path": "/shots/tr"}, {"op": "replace", "path": "/shots/list_display_order", "value": "qa,hf,xc,ka,fn"}], "validation_labels": []}